staircase/__init__.py
staircase/cli.py
staircase/command_providers.py
staircase/commands/__init__.py
staircase/commands/asana/__init__.py
staircase/commands/asana/searches.py
staircase/commands/ci.py
staircase/commands/config/__init__.py
staircase/commands/config/file_path.py
staircase/commands/config/setup.py
staircase/commands/envs/__init__.py
staircase/commands/envs/add.py
staircase/commands/envs/list.py
staircase/commands/envs/remove.py
staircase/commands/health/__init__.py
staircase/commands/health/metrics.py
staircase/commands/health/set_health_check.py
staircase/commands/marketplace/subscribe.py
staircase/commands/postman/__init__.py
staircase/commands/postman/import_/__init__.py
staircase/commands/postman/import_/api.py
staircase/commands/postman/import_/envs.py
staircase/config.py
staircase/env_manager.py
staircase/env_storage.py
staircase/lib/__init__.py
staircase/lib/click.py
staircase/lib/fzf.py
staircase/lib/postman_http_client.py
staircase/lib/sdk/__init__.py
staircase/lib/sdk/ci/__init__.py
staircase/lib/sdk/ci/assess.py
staircase/lib/sdk/ci/build.py
staircase/lib/sdk/ci/clone.py
staircase/lib/sdk/ci/deploy.py
staircase/lib/sdk/ci/test.py
staircase/lib/sdk/staircase_env.py
staircase/lib/sdk/staircase_http_client.py
staircase/lib/shutil.py
staircase/logger.py
staircase/postman.py
staircase/staircase.py
staircase/staircase_asana.py
staircase/user_prompts.py
staircase_kit-0.1.39.dist-info/METADATA
staircase_kit-0.1.39.dist-info/WHEEL
staircase_kit-0.1.39.dist-info/entry_points.txt
staircase_kit-0.1.39.dist-info/RECORD
