Metadata-Version: 2.1
Name: staircase-kit
Version: 0.1.39
Summary: 
Author: Zik
Author-email: zikunov.vladislav@staircase.co
Requires-Python: >=3.8,<4.0
Classifier: Programming Language :: Python :: 3
Classifier: Programming Language :: Python :: 3.8
Classifier: Programming Language :: Python :: 3.9
Classifier: Programming Language :: Python :: 3.10
Classifier: Programming Language :: Python :: 3.11
Classifier: Programming Language :: Python :: 3.12
Requires-Dist: aiohttp (==3.*)
Requires-Dist: aiostream
Requires-Dist: asana (>=3.2.1,<4.0.0)
Requires-Dist: boto3
Requires-Dist: click
Requires-Dist: cryptography
Requires-Dist: curlify
Requires-Dist: mypy
Requires-Dist: plumbum
Requires-Dist: pydantic
Requires-Dist: python-ulid (>=1.1.0,<2.0.0)
Requires-Dist: pyyaml
Requires-Dist: requests (>=2.28.2,<3.0.0)
Requires-Dist: rich
Requires-Dist: uncurl
